arrow_tests/__init__.py
arrow_tests/conftest.py
arrow_tests/test_api.py
arrow_tests/test_arrow.py
arrow_tests/test_factory.py
arrow_tests/test_formatter.py
arrow_tests/test_locales.py
arrow_tests/test_parser.py
arrow_tests/test_util.py
arrow_tests/utils.py
jp_arrow/__init__.py
jp_arrow/api.py
jp_arrow/arrow.py
jp_arrow/factory.py
jp_arrow/formatter.py
jp_arrow/jp_date.py
jp_arrow/version.py
jp_arrow-0.1.1.dist-info/LICENSE
jp_arrow-0.1.1.dist-info/METADATA
jp_arrow-0.1.1.dist-info/WHEEL
jp_arrow-0.1.1.dist-info/top_level.txt
jp_arrow-0.1.1.dist-info/RECORD
