Metadata-Version: 2.1
Name: jp-arrow
Version: 0.1.1
Summary: Convert date/datetime from/to Japanese date/datetime
Home-page: https://github.com/iisaka51/jp_arrow
Author: iisaka51
Author-email: iisaka51@gmail.com
License: Apache 2.0
Keywords: arrow date time datetime timestamp timezone humanize
Classifier: License :: OSI Approved :: Apache Software License
Classifier: Programming Language :: Python :: 3.8
Classifier: Programming Language :: Python :: 3.9
Classifier: Programming Language :: Python :: 3.10
License-File: LICENSE
Requires-Dist: arrrow
